cymepy/__init__.py
cymepy/common.py
cymepy/cymepy.py
cymepy/device_obj.py
cymepy/helics_interface.py
cymepy/logger.py
cymepy/run.py
cymepy/solver.py
cymepy/validators.py
cymepy/cli/__init__.py
cymepy/cli/cymepy.py
cymepy/cli/run.py
cymepy/defaults/__init__.py
cymepy/defaults/publications.toml
cymepy/defaults/settings.toml
cymepy/defaults/subscriptions.toml
cymepy/export_manager/__init__.py
cymepy/export_manager/base_definations.py
cymepy/export_manager/common.py
cymepy/export_manager/hooks/JSON_writer.py
cymepy/export_manager/hooks/__init__.py
cymepy/export_manager/hooks/csv_writer.py
cymepy/export_manager/hooks/h5_writer.py
cymepy/profile_manager/__init__.py
cymepy/profile_manager/base_definations.py
cymepy/profile_manager/common.py
cymepy/profile_manager/hooks/ACCESS.py
cymepy/profile_manager/hooks/HDF5.py
cymepy/profile_manager/hooks/__init__.py
cymepy/utils/__init__.py
cymepy/utils/utils.py
cymepy-0.0.8.dist-info/LICENSE
cymepy-0.0.8.dist-info/METADATA
cymepy-0.0.8.dist-info/WHEEL
cymepy-0.0.8.dist-info/entry_points.txt
cymepy-0.0.8.dist-info/top_level.txt
cymepy-0.0.8.dist-info/RECORD
