Metadata-Version: 2.1
Name: cymepy
Version: 0.0.8
Summary: Helice interface for CYME
Home-page: https://github.com/GMLC-TDC/cymepy
Author: Aadil Latif
Author-email: Aadil.Latif@nrel.gov
License: BSD 3 clause
Platform: UNKNOWN
Classifier: Development Status :: 4 - Beta
Classifier: Environment :: Console
Classifier: Environment :: Web Environment
Classifier: Intended Audience :: Developers
Classifier: Intended Audience :: Science/Research
Classifier: Operating System :: OS Independent
Classifier: Programming Language :: Python :: 3
Classifier: License :: OSI Approved :: BSD License
Requires-Python: >=3.6
License-File: LICENSE
Requires-Dist: pandas
Requires-Dist: helics
Requires-Dist: terminaltables
Requires-Dist: click
Requires-Dist: pydantic
Requires-Dist: toml
Requires-Dist: h5py
Requires-Dist: pyodbc
